Night/__init__.py
Night/main.py
mrNyct-0.1.dist-info/METADATA
mrNyct-0.1.dist-info/WHEEL
mrNyct-0.1.dist-info/top_level.txt
mrNyct-0.1.dist-info/RECORD
