Metadata-Version: 2.1
Name: mrNyct
Version: 0.1
Summary: A Python package to install external libraries that we need in my code
Author: Nyctophile
Author-email: shanumartin3@gmail.com
